{
  "annotations": {
    "list": [
      {
        "builtIn": 1,
        "datasource": {
          "type": "grafana",
          "uid": "-- Grafana --"
        },
        "enable": true,
        "hide": true,
        "iconColor": "rgba(0, 211, 255, 1)",
        "name": "Annotations & Alerts",
        "type": "dashboard"
      }
    ]
  },
  "editable": true,
  "fiscalYearStartMonth": 0,
  "graphTooltip": 0,
  "id": 6,
  "links": [],
  "panels": [
  ],
  "schemaVersion": 39,
  "tags": [],
  "templating": {
    "list": [
      {
        "current": {
          "selected": false,
          "text": "nhs-notify-main",
          "value": "nhs-notify-main"
        },
        "description": "",
        "hide": 0,
        "label": "Environment CSI Prefix",
        "name": "envCsi",
        "options": [
          {
            "selected": true,
            "text": "nhs-notify-main",
            "value": "nhs-notify-main"
          }
        ],
        "query": "nhs-notify-main",
        "skipUrlSync": false,
        "type": "textbox"
      },
      {
        "current": {
          "selected": false,
          "text": "CloudWatch-web-gateway",
          "value": "befiv6gq7pq80a"
        },
        "hide": 0,
        "includeAll": false,
        "label": "Datasource",
        "multi": false,
        "name": "datasrc",
        "options": [],
        "query": "cloudwatch",
        "queryValue": "",
        "refresh": 1,
        "regex": ".*-core-.*",
        "skipUrlSync": false,
        "type": "datasource"
      }
    ]
  },
  "time": {
    "from": "now-1d",
    "to": "now"
  },
  "timepicker": {},
  "timezone": "browser",
  "title": "Core Routing Overview",
  "uid": "",
  "version": 1,
  "weekStart": ""
}
